{
    "os": "Linux-5.15.0-89-generic-x86_64-with-glibc2.31",
    "python": "3.10.12",
    "heartbeatAt": "2023-12-23T16:37:14.543309",
    "startedAt": "2023-12-23T16:37:14.443226",
    "docker": null,
    "cuda": null,
    "args": [
        "--c",
        "./configs/eval.yaml"
    ],
    "state": "running",
    "program": "/home/hcis-s17/YongZhe/ke2/FGVC/main_bird.py",
    "codePathLocal": "main_bird.py",
    "codePath": "main_bird.py",
    "git": {
        "remote": "https://github.com/chou141253/FGVC-PIM.git",
        "commit": "348edd983d0007a0cbbce65979aa2fbaade068c8"
    },
    "email": null,
    "root": "/home/hcis-s17/YongZhe/ke2/FGVC",
    "host": "hcis-s17",
    "username": "hcis-s17",
    "executable": "/home/hcis-s17/miniconda3/envs/FINAL/bin/python",
    "cpu_count": 12,
    "cpu_count_logical": 20,
    "cpu_freq": {
        "current": 2344.9192,
        "min": 800.0,
        "max": 4580.0
    },
    "cpu_freq_per_core": [
        {
            "current": 4487.036,
            "min": 800.0,
            "max": 4800.0
        },
        {
            "current": 2100.0,
            "min": 800.0,
            "max": 4800.0
        },
        {
            "current": 2100.0,
            "min": 800.0,
            "max": 4800.0
        },
        {
            "current": 4467.192,
            "min": 800.0,
            "max": 4800.0
        },
        {
            "current": 2100.0,
            "min": 800.0,
            "max": 4800.0
        },
        {
            "current": 2100.0,
            "min": 800.0,
            "max": 4800.0
        },
        {
            "current": 2100.0,
            "min": 800.0,
            "max": 4800.0
        },
        {
            "current": 2100.0,
            "min": 800.0,
            "max": 4800.0
        },
        {
            "current": 2100.0,
            "min": 800.0,
            "max": 4900.0
        },
        {
            "current": 2100.0,
            "min": 800.0,
            "max": 4900.0
        },
        {
            "current": 2100.0,
            "min": 800.0,
            "max": 4900.0
        },
        {
            "current": 2100.0,
            "min": 800.0,
            "max": 4900.0
        },
        {
            "current": 4611.348,
            "min": 800.0,
            "max": 4800.0
        },
        {
            "current": 2100.0,
            "min": 800.0,
            "max": 4800.0
        },
        {
            "current": 2100.0,
            "min": 800.0,
            "max": 4800.0
        },
        {
            "current": 2100.0,
            "min": 800.0,
            "max": 4800.0
        },
        {
            "current": 2100.0,
            "min": 800.0,
            "max": 3600.0
        },
        {
            "current": 2100.0,
            "min": 800.0,
            "max": 3600.0
        },
        {
            "current": 2100.0,
            "min": 800.0,
            "max": 3600.0
        },
        {
            "current": 2100.0,
            "min": 800.0,
            "max": 3600.0
        }
    ],
    "disk": {
        "/": {
            "total": 937.3305015563965,
            "used": 816.118824005127
        }
    },
    "gpu": "NVIDIA GeForce GTX 1080 Ti",
    "gpu_count": 1,
    "gpu_devices": [
        {
            "name": "NVIDIA GeForce GTX 1080 Ti",
            "memory_total": 11811160064
        }
    ],
    "memory": {
        "total": 31.08626937866211
    }
}
